arrakis_schema/__init__.py
arrakis_schema/_version.py
arrakis_schema/count.json
arrakis_schema/describe.json
arrakis_schema/descriptor.json
arrakis_schema/find.json
arrakis_schema/partition.json
arrakis_schema/publish.json
arrakis_schema/stream.json
arrakis_schema-0.1.2.dist-info/METADATA
arrakis_schema-0.1.2.dist-info/WHEEL
arrakis_schema-0.1.2.dist-info/licenses/LICENSE
arrakis_schema-0.1.2.dist-info/RECORD
