Metadata-Version: 2.4
Name: arrakis-schema
Version: 0.1.2
Summary: Schemas for the Arrakis API
Project-URL: Homepage, https://git.ligo.org/ngdd/arrakis-schema
Project-URL: Documentation, https://docs.ligo.org/ngdd/arrakis-schema
Project-URL: Issue Tracker, https://git.ligo.org/ngdd/arrakis-schema/issues
Project-URL: Source Code, https://git.ligo.org/ngdd/arrakis-schema.git
Author-email: Patrick Godwin <patrick.godwin@ligo.org>, Jameson Graef Rollins <jameson.rollins@ligo.org>
Maintainer-email: Patrick Godwin <patrick.godwin@ligo.org>
License-Expression: LGPL-3.0-or-later
License-File: LICENSE
Classifier: Development Status :: 3 - Alpha
Classifier: Intended Audience :: Developers
Classifier: Intended Audience :: Science/Research
Classifier: License :: OSI Approved :: GNU General Public License v3 or later (GPLv3+)
Classifier: Natural Language :: English
Classifier: Operating System :: POSIX
Classifier: Operating System :: POSIX :: Linux
Classifier: Programming Language :: Python
Classifier: Programming Language :: Python :: 3
Classifier: Topic :: Scientific/Engineering
Classifier: Topic :: Scientific/Engineering :: Astronomy
Classifier: Topic :: Scientific/Engineering :: Physics
Requires-Python: >=3.10
Requires-Dist: importlib-resources>=5.10; python_version < '3.12'
Provides-Extra: dev
Requires-Dist: arrakis[docs]; extra == 'dev'
Requires-Dist: arrakis[lint]; extra == 'dev'
Requires-Dist: arrakis[test]; extra == 'dev'
Provides-Extra: docs
Requires-Dist: markdown-callouts>=0.2; extra == 'docs'
Requires-Dist: markdown-exec>=0.5; extra == 'docs'
Requires-Dist: mkdocs-coverage>=0.2; extra == 'docs'
Requires-Dist: mkdocs-gen-files>=0.3; extra == 'docs'
Requires-Dist: mkdocs-literate-nav>=0.4; extra == 'docs'
Requires-Dist: mkdocs-material-igwn; extra == 'docs'
Requires-Dist: mkdocs-section-index>=0.3; extra == 'docs'
Requires-Dist: mkdocs>=1.3; extra == 'docs'
Requires-Dist: mkdocstrings[python]; extra == 'docs'
Requires-Dist: toml>=0.10; extra == 'docs'
Provides-Extra: lint
Requires-Dist: mypy; extra == 'lint'
Requires-Dist: mypy-extensions; extra == 'lint'
Requires-Dist: pip; extra == 'lint'
Requires-Dist: ruff; extra == 'lint'
Provides-Extra: test
Requires-Dist: pytest; extra == 'test'
Requires-Dist: pytest-cov; extra == 'test'
